simfret/__init__.py
simfret/compute.py
simfret/compute_utils.py
simfret/fretraj.py
simfret/overlap.py
simfret/overlap_utils.py
simfret/simulate.py
simfret/suggest.py
simfret/suggest_utils.py
simfret/testing.py
SimFRET-0.0.1.dist-info/LICENSE
SimFRET-0.0.1.dist-info/METADATA
SimFRET-0.0.1.dist-info/WHEEL
SimFRET-0.0.1.dist-info/top_level.txt
SimFRET-0.0.1.dist-info/RECORD
