Metadata-Version: 2.1
Name: SimFRET
Version: 0.0.1
Summary: A Python package to simulate FRET experiments.
Home-page: https://github.com/diegoeduardok/SimFRET
Author: Diego Kleiman
Author-email: diegokleiman@hotmail.com
License: UNKNOWN
Platform: UNKNOWN
Classifier: Programming Language :: Python :: 3
Classifier: License :: OSI Approved :: BSD License
Classifier: Operating System :: OS Independent
Requires-Python: >=3.7.6
